trimes/__init__.py
trimes/base.py
trimes/comparison.py
trimes/control.py
trimes/derivative.py
trimes/electrical.py
trimes/filter.py
trimes/fourier.py
trimes/metrics.py
trimes/plots.py
trimes/regression.py
trimes/root_mean_square.py
trimes/signal_generation.py
trimes/signal_processing.py
trimes/transforms.py
trimes-0.0.7.dist-info/METADATA
trimes-0.0.7.dist-info/WHEEL
trimes-0.0.7.dist-info/licenses/LICENSE
trimes-0.0.7.dist-info/RECORD
