Metadata-Version: 2.3
Name: trimes
Version: 0.0.7
Summary: A python package for transient time series
Project-URL: Homepage, https://github.com/FraunhIEE-UniKassel-PowSysStability/trimes
Project-URL: Bug Tracker, https://github.com/FraunhIEE-UniKassel-PowSysStability/trimes/issues
Author-email: Sciemon <simon.eberlein@gmx.de>
License: MIT License
Classifier: License :: OSI Approved :: MIT License
Classifier: Operating System :: OS Independent
Classifier: Programming Language :: Python :: 3
Requires-Python: >=3.10
Requires-Dist: control>0.10
Requires-Dist: icecream>=2.1.2
Requires-Dist: matplotlib>3
Requires-Dist: numpy>=2.1.3
Requires-Dist: pandas>=2.2.3
